{
  "anchor_modes": {
    "article_fallback": 630,
    "exact": 5663,
    "norma_fallback": 16
  },
  "append_vademecum": {
    "appended": 6291,
    "enabled": true
  },
  "detalhes_total": 4011,
  "fetch_errors": {},
  "linhas_com_alerta_qualidade": 16,
  "linhas_qordem_geradas": 6307,
  "linhas_selecionadas_para_append_import": 6291,
  "notion": {
    "data_source_id": "9a9d17ea-79b7-41ae-83a8-534afd9dde58",
    "database_url": "https://www.notion.so/43dc0febe1ea447fa5fa8c9b21670ce7",
    "missing_pages": 0,
    "missing_parent_pages": 0,
    "relation_result": {
      "missing_parent": 0,
      "pending": 6291,
      "total_marked": 35429,
      "updated": 6291
    },
    "relations_marked": 6291,
    "rows": 6291
  },
  "notion_direct_validation_after_cleanup": {
    "duplicate_count": 0,
    "duplicates": [],
    "missing_relation": [],
    "missing_row_key": 0,
    "questao_ordem_pages": 6291,
    "relations_present": 6291
  },
  "questoes_com_linhas": 2805,
  "questoes_sem_dispositivo_regimental": 1206,
  "row_keys_duplicadas_geracao": 0,
  "source_cached_detail_ids": 4011,
  "source_listed_qordem_ids": 4056,
  "source_missing_detail_count": 45,
  "source_missing_detail_ids": [
    23278,
    23318,
    23320,
    23327,
    23340,
    23361,
    23364,
    23369,
    23394,
    23395,
    23400,
    23409,
    23412,
    23415,
    23435,
    23442,
    23443,
    23444,
    23446,
    23450,
    23461,
    23462,
    23463,
    23464,
    23467,
    23468,
    23470,
    23476,
    23477,
    23480,
    23482,
    23489,
    23490,
    23494,
    23496,
    23497,
    23498,
    23523,
    23526,
    23527,
    23641,
    23649,
    23654,
    23838,
    24218
  ],
  "validacao_local": {
    "duplicate_row_keys": 0,
    "missing_parent_key": 0,
    "missing_source_url": 0,
    "missing_texto_rag": 0,
    "quality_review": 16,
    "rows": 6307
  }
}